gera/__init__.py
gera/__main__.py
gera/application.py
gera/dbutils.py
gera/main_window.py
gera/mdi_area.py
gera/report_window.py
gera/sql_text_edit.py
gera/utils.py
gera/resources/cascade.svg
gera/resources/fullscreen.svg
gera/resources/gera.svg
gera/resources/menu.svg
gera/resources/next.svg
gera/resources/open.svg
gera/resources/prev.svg
gera/resources/tile.svg
gera/resources/tile_h.svg
gera/resources/tile_v.svg
gera/schemas/__init__.py
gera/schemas/ldj.py
gera-0.1.0.dist-info/METADATA
gera-0.1.0.dist-info/WHEEL
gera-0.1.0.dist-info/entry_points.txt
gera-0.1.0.dist-info/top_level.txt
gera-0.1.0.dist-info/RECORD
