Metadata-Version: 2.1
Name: gera
Version: 0.1.0
Summary: General ERror Analyzer
Author-email: Arseniy Terekhin <senyai@gmail.com>
Classifier: Programming Language :: Python :: 3
Classifier: License :: OSI Approved :: MIT License
Classifier: Operating System :: OS Independent
Requires-Python: >=3.10
Requires-Dist: PyQt5
